screeny/__init__.py
screeny/__main__.py
screeny/image_compression.py
screeny/server.py
mcp_server_screeny-0.3.6.dist-info/METADATA
mcp_server_screeny-0.3.6.dist-info/WHEEL
mcp_server_screeny-0.3.6.dist-info/entry_points.txt
mcp_server_screeny-0.3.6.dist-info/licenses/LICENSE
mcp_server_screeny-0.3.6.dist-info/RECORD
