Metadata-Version: 2.4
Name: mcp-server-screeny
Version: 0.3.6
Summary: macOS MCP server for window enumeration and screenshot capture
Author-email: Rohan Ravindran <r8ravind@uwaterloo.ca>
License: MIT
License-File: LICENSE
Keywords: macos,mcp,screenshot,server,window
Classifier: Development Status :: 4 - Beta
Classifier: Intended Audience :: Developers
Classifier: License :: OSI Approved :: MIT License
Classifier: Operating System :: MacOS
Classifier: Programming Language :: Python :: 3
Classifier: Programming Language :: Python :: 3.10
Classifier: Programming Language :: Python :: 3.11
Classifier: Programming Language :: Python :: 3.12
Requires-Python: >=3.10
Requires-Dist: mcp>=1.9.0
Requires-Dist: pillow>=10.0.0
Requires-Dist: pyobjc-framework-quartz>=10.0
